open_nipals/__init__.py
open_nipals/nipalsPCA.py
open_nipals/nipalsPLS.py
open_nipals/utils.py
open_nipals-2.0.1.dist-info/licenses/AUTHORS.md
open_nipals-2.0.1.dist-info/licenses/LICENSE.txt
open_nipals-2.0.1.dist-info/METADATA
open_nipals-2.0.1.dist-info/WHEEL
open_nipals-2.0.1.dist-info/top_level.txt
open_nipals-2.0.1.dist-info/RECORD
