Metadata-Version: 2.4
Name: open_nipals
Version: 2.0.1
Summary: A package to support dimensionality reduction methods.
Home-page: https://github.com/johnsonandjohnson/open_nipals/pull/13
Author: 'Niels Schlusser'
Author-email: nschluss@its.jnj.com
License: BSD 3-Clause License
Project-URL: Documentation, https://about.readthedocs.com/
Platform: any
Classifier: Development Status :: 4 - Beta
Classifier: Programming Language :: Python
Requires-Python: <3.15,>=3.9
License-File: LICENSE.txt
License-File: AUTHORS.md
Requires-Dist: numpy<2.4,>=1.21
Requires-Dist: pandas<2.4,>=2.0
Requires-Dist: scipy<1.17,>=1.5
Requires-Dist: scikit-learn<1.8,>=1.2
Provides-Extra: testing
Requires-Dist: setuptools; extra == "testing"
Requires-Dist: pytest; extra == "testing"
Requires-Dist: pytest-cov; extra == "testing"
Requires-Dist: parameterized; extra == "testing"
Requires-Dist: openpyxl; extra == "testing"
Requires-Dist: ruff; extra == "testing"
Requires-Dist: tox; extra == "testing"
Requires-Dist: tox-conda; extra == "testing"
Dynamic: license-file
